JiyuQukuaiLianJishuShixianDeXueliXinxiZhengxinXitong/README.md
JiyuQukuaiLianJishuShixianDeXueliXinxiZhengxinXitong/__init__.py
JiyuQukuaiLianJishuShixianDeXueliXinxiZhengxinXitong/__main__.py
JiyuQukuaiLianJishuShixianDeXueliXinxiZhengxinXitong/file.epub
JiyuQukuaiLianJishuShixianDeXueliXinxiZhengxinXitong/index.html
JiyuQukuaiLianJishuShixianDeXueliXinxiZhengxinXitong/css/__init__.py
JiyuQukuaiLianJishuShixianDeXueliXinxiZhengxinXitong/css/annotations.css
JiyuQukuaiLianJishuShixianDeXueliXinxiZhengxinXitong/css/main.css
JiyuQukuaiLianJishuShixianDeXueliXinxiZhengxinXitong/css/normalize.css
JiyuQukuaiLianJishuShixianDeXueliXinxiZhengxinXitong/css/popup.css
JiyuQukuaiLianJishuShixianDeXueliXinxiZhengxinXitong/font/__init__.py
JiyuQukuaiLianJishuShixianDeXueliXinxiZhengxinXitong/font/fontello.eot
JiyuQukuaiLianJishuShixianDeXueliXinxiZhengxinXitong/font/fontello.svg
JiyuQukuaiLianJishuShixianDeXueliXinxiZhengxinXitong/font/fontello.ttf
JiyuQukuaiLianJishuShixianDeXueliXinxiZhengxinXitong/font/fontello.woff
JiyuQukuaiLianJishuShixianDeXueliXinxiZhengxinXitong/img/__init__.py
JiyuQukuaiLianJishuShixianDeXueliXinxiZhengxinXitong/img/annotator-glyph-sprite.png
JiyuQukuaiLianJishuShixianDeXueliXinxiZhengxinXitong/img/annotator-icon-sprite.png
JiyuQukuaiLianJishuShixianDeXueliXinxiZhengxinXitong/img/apple-touch-icon.png
JiyuQukuaiLianJishuShixianDeXueliXinxiZhengxinXitong/img/cancelfullscreen.png
JiyuQukuaiLianJishuShixianDeXueliXinxiZhengxinXitong/img/close.png
JiyuQukuaiLianJishuShixianDeXueliXinxiZhengxinXitong/img/fullscreen.png
JiyuQukuaiLianJishuShixianDeXueliXinxiZhengxinXitong/img/loader.gif
JiyuQukuaiLianJishuShixianDeXueliXinxiZhengxinXitong/img/menu-icon.png
JiyuQukuaiLianJishuShixianDeXueliXinxiZhengxinXitong/img/save.png
JiyuQukuaiLianJishuShixianDeXueliXinxiZhengxinXitong/img/saved.png
JiyuQukuaiLianJishuShixianDeXueliXinxiZhengxinXitong/img/settings-s.png
JiyuQukuaiLianJishuShixianDeXueliXinxiZhengxinXitong/img/settings.png
jiyu_qukuai_lian_jishu_shixian_de_xueli_xinxi_zhengxin_xitong-2024.3.4.0.dist-info/METADATA
jiyu_qukuai_lian_jishu_shixian_de_xueli_xinxi_zhengxin_xitong-2024.3.4.0.dist-info/WHEEL
jiyu_qukuai_lian_jishu_shixian_de_xueli_xinxi_zhengxin_xitong-2024.3.4.0.dist-info/entry_points.txt
jiyu_qukuai_lian_jishu_shixian_de_xueli_xinxi_zhengxin_xitong-2024.3.4.0.dist-info/top_level.txt
jiyu_qukuai_lian_jishu_shixian_de_xueli_xinxi_zhengxin_xitong-2024.3.4.0.dist-info/RECORD
